nwbindexer/__init__.py
nwbindexer/build_index.py
nwbindexer/query_index.py
nwbindexer/search_nwb.py
nwbindexer/speed_check.py
nwbindexer/lib/__init__.py
nwbindexer/lib/make_sql.py
nwbindexer/lib/pack_values.py
nwbindexer/lib/parse.py
nwbindexer/lib/results.py
nwbindexer/test/ecephys_example.nwb
nwbindexer/test/example_file_path.nwb
nwbindexer/test/ophys_example.nwb
nwbindexer/test/test_all.py
nwbindexer-0.1.3.dist-info/METADATA
nwbindexer-0.1.3.dist-info/WHEEL
nwbindexer-0.1.3.dist-info/entry_points.txt
nwbindexer-0.1.3.dist-info/top_level.txt
nwbindexer-0.1.3.dist-info/RECORD
