Metadata-Version: 2.1
Name: nwbindexer
Version: 0.1.3
Summary: Two tools for searching data stored using the NWB (Neurodata Without Borders) format
Home-page: https://github.com/jeffteeters/nwbindexer
Author: Jeff Teeters
Author-email: jeff@teeters.us
License: UNKNOWN
Platform: UNKNOWN
Classifier: Programming Language :: Python :: 3
Classifier: Operating System :: OS Independent
Requires-Python: >=3.7
Requires-Dist: parsimonious (>=0.8.1)
Requires-Dist: h5py (>=2.9)
Requires-Dist: numpy
